nonebot_plugin_SDGPT/__init__.py
nonebot_plugin_SDGPT/bot.py
nonebot_plugin_SDGPT/config.py
nonebot_plugin_SDGPT/configspec.ini
nonebot_plugin_SDGPT/lib/base.py
nonebot_plugin_SDGPT/lib/check.py
nonebot_plugin_SDGPT/lib/cons.py
nonebot_plugin_SDGPT/lib/logger.py
nonebot_plugin_SDGPT/lib/test.py
nonebot_plugin_SDGPT/lib/utils.py
nonebot_plugin_sdgpt-0.2.8.dist-info/LICENSE
nonebot_plugin_sdgpt-0.2.8.dist-info/METADATA
nonebot_plugin_sdgpt-0.2.8.dist-info/WHEEL
nonebot_plugin_sdgpt-0.2.8.dist-info/RECORD
