Metadata-Version: 2.1
Name: nonebot-plugin-sdgpt
Version: 0.2.8
Summary: ChatBot for NoneBot : 链接 ChatGPT / Bing / Poe / Stable-Diffusion : ChatGPT Bing poe聊天, gpt解析自然语言转Stable-Diffusion生成图像
Home-page: https://github.com/thx114/SDGPT
License: MIT
Keywords: nonebot,nonebot2,chatgpt,new bing,Stable-Diffusion
Author: F_thx
Author-email: thx1140093097@gmail.com
Requires-Python: >=3.8,<4.0
Classifier: License :: OSI Approved :: MIT License
Classifier: Programming Language :: Python :: 3
Classifier: Programming Language :: Python :: 3.8
Classifier: Programming Language :: Python :: 3.9
Classifier: Programming Language :: Python :: 3.10
Classifier: Programming Language :: Python :: 3.11
Provides-Extra: onebot
Requires-Dist: EdgeGPT (>=0.1.25.1,<0.2.0.0)
Requires-Dist: aiofiles
Requires-Dist: configobj
Requires-Dist: nonebot-adapter-onebot (>=2.0.0-beta.1,<3.0.0) ; extra == "onebot"
Requires-Dist: nonebot-plugin-guild-patch
Requires-Dist: nonebot2 (>=2.0.0-beta.1,<3.0.0)
Requires-Dist: poe-api (>=0.2.12,<0.3.0)
Requires-Dist: python-dotenv
Requires-Dist: revChatGPT (>=5.0.0,<6.0.0)
Requires-Dist: websockets (>=10.0,<11.0)
Requires-Dist: webuiapi
Project-URL: Documentation, https://github.com/thx114/SDGPTreadme
Project-URL: Repository, https://github.com/thx114/SDGPT
